Workbook

Sheet Decisão
A1: 17 NFs sem pagamento identificado: decisão consolidada com as evidências da pasta Tesouraria
A2: Versão 3, de 13/10/2026. Células VERDES foram preenchidas pelas evidências da pasta (justificativa e arquivo nas colunas X e Y). Células AMARELAS esperam a sua decisão; laranja = falta preencher. Nada foi alterado no app: nenhum lançamento, movimentação ou reclassificação.
A3: O QUE SABEMOS | O3: RASTREAR PELA NF-e | R3: SITUAÇÃO | W3: EVIDÊNCIA DA PASTA | Z3: O QUE AINDA FALTA
A4: ID | B4: Fornecedor | C4: CNPJ do emitente | D4: Endereço do emitente | E4: Nº da NF | F4: Data | G4: Valor (R$) | H4: Categoria atual | I4: Centro atual | J4: Descrição | K4: Existe documento anexado? | L4: Existe pagamento localizado? | M4: Observações | N4: Confiança e fonte do CNPJ e endereço | O4: Chave de acesso da NF-e (44 dígitos) | P4: CNPJ pela chave (automático) | Q4: Consultar emitente (automático) | R4: Situação | S4: Nome do doador (se Oferta) | T4: Pessoa a reembolsar (se Reembolso) | U4: Pagamento já realizado? (se Reembolso) | V4: Forma de pagamento (se Pago de Outra Forma) | W4: Origem da classificação | X4: Justificativa | Y4: Documento utilizado | Z4: Pendência restante | AA4: Próximo passo | AB4: Sua observação
A5: NF-01 | B5: RFC Comércio de Miudezas | C5: Não identificado | D5: — | E5: 6942 | F5: 45955.625 | G5: 125.88 | H5: Sem lançamento no app | I5: — | J5: NF 6942, RFC Comércio de Miudezas. Nota recebida e lançada pelo escritório na conta 211005 (fornecedores de bens materiais), ainda sem baixa. | K5: Não (a NF não está no app nem na pasta) | L5: Não | M5: Pelo nome: material diverso (miudezas). Fornecedor sem cadastro no app. Aberta há 310 dias em 31/08/2026. | N5: Não identificado só pelo nome. A busca por nome em bases públicas devolveu empresas de nome parecido, nenhuma confirmada. Use a chave de acesso da NF-e (colunas O a Q). | P5: =IF(LEN(SUBSTITUTE($O5," ",""))=44,MID(SUBSTITUTE($O5," ",""),7,2)&"."&MID(SUBSTITUTE($O5," ",""),9,3)&"."&MID(SUBSTITUTE($O5," ",""),12,3)&"/"&MID(SUBSTITUTE($O5," ",""),15,4)&"-"&MID(SUBSTITUTE($O5," ",""),19,2),"") | Q5: =IF(LEN(SUBSTITUTE($O5," ",""))=44,HYPERLINK("https://cnpja.com/office/"&MID(SUBSTITUTE($O5," ",""),7,14),"Consultar emitente"),"") | W5: Aguarda decisão da igreja | X5: Nenhuma evidência na pasta Tesouraria: busquei por nome do arquivo, número da NF, valor (±R$ 0,01, até 90 dias) e pelo TEXTO de 3.601 PDFs. Nada do fornecedor, da NF nem do valor. (889 PDFs são imagens e não puderam ser lidos por texto.) | Y5: — | Z5: Decisão; Resposta do escritório (chave da NF-e) | AA5: Decidir a situação (oferta, reembolso, pago de outra forma, NF cancelada ou investigar) e pedir ao escritório a chave de acesso da NF-e.
A6: NF-02 | B6: Kalunga | C6: 43.283.811/0001-50 (matriz) | D6: Rua da Mooca, 766, andares 4 e 5, Mooca, São Paulo/SP, CEP 03104-010. Tel. (11) 3346-9600. Razão social: KALUNGA SA. | E6: 344169 | F6: 45957.625 | G6: 84.2 | H6: Sem lançamento no app | I6: — | J6: NF 344169, Kalunga. Nota recebida e lançada pelo escritório na conta 211005 (fornecedores de bens materiais), ainda sem baixa. | K6: Não (a NF não está no app nem na pasta) | L6: Não | M6: Pela Receita: papelaria. Fornecedor sem cadastro no app. Aberta há 308 dias em 31/08/2026. | N6: Matriz confirmada na Receita (a razão social confere). A NF pode ter saído de uma filial (a Kalunga tem lojas no Rio, como Norte Shopping/Cachambi): a chave diz qual. | P6: =IF(LEN(SUBSTITUTE($O6," ",""))=44,MID(SUBSTITUTE($O6," ",""),7,2)&"."&MID(SUBSTITUTE($O6," ",""),9,3)&"."&MID(SUBSTITUTE($O6," ",""),12,3)&"/"&MID(SUBSTITUTE($O6," ",""),15,4)&"-"&MID(SUBSTITUTE($O6," ",""),19,2),"") | Q6: =IF(LEN(SUBSTITUTE($O6," ",""))=44,HYPERLINK("https://cnpja.com/office/"&MID(SUBSTITUTE($O6," ",""),7,14),"Consultar emitente"),"") | W6: Aguarda decisão da igreja | X6: Nenhuma evidência na pasta Tesouraria: busquei por nome do arquivo, número da NF, valor (±R$ 0,01, até 90 dias) e pelo TEXTO de 3.601 PDFs. Nada do fornecedor, da NF nem do valor. (889 PDFs são imagens e não puderam ser lidos por texto.) | Y6: — | Z6: Decisão; Resposta do escritório (chave da NF-e) | AA6: Decidir a situação (oferta, reembolso, pago de outra forma, NF cancelada ou investigar) e pedir ao escritório a chave de acesso da NF-e.
A7: NF-03 | B7: Vira Verão Bazar | C7: Não identificado | D7: — | E7: 64 | F7: 45958.625 | G7: 25 | H7: Sem lançamento no app | I7: — | J7: NF 64, Vira Verão Bazar. Nota recebida e lançada pelo escritório na conta 211005 (fornecedores de bens materiais), ainda sem baixa. | K7: Não (a NF não está no app nem na pasta) | L7: Não | M7: Pelo nome: bazar, artigos diversos. Fornecedor sem cadastro no app. Aberta há 307 dias em 31/08/2026. | N7: Não identificado só pelo nome. A busca por nome em bases públicas devolveu empresas de nome parecido, nenhuma confirmada. Use a chave de acesso da NF-e (colunas O a Q). | P7: =IF(LEN(SUBSTITUTE($O7," ",""))=44,MID(SUBSTITUTE($O7," ",""),7,2)&"."&MID(SUBSTITUTE($O7," ",""),9,3)&"."&MID(SUBSTITUTE($O7," ",""),12,3)&"/"&MID(SUBSTITUTE($O7," ",""),15,4)&"-"&MID(SUBSTITUTE($O7," ",""),19,2),"") | Q7: =IF(LEN(SUBSTITUTE($O7," ",""))=44,HYPERLINK("https://cnpja.com/office/"&MID(SUBSTITUTE($O7," ",""),7,14),"Consultar emitente"),"") | W7: Aguarda decisão da igreja | X7: Nenhuma evidência na pasta Tesouraria: busquei por nome do arquivo, número da NF, valor (±R$ 0,01, até 90 dias) e pelo TEXTO de 3.601 PDFs. Nada do fornecedor, da NF nem do valor. (889 PDFs são imagens e não puderam ser lidos por texto.) | Y7: — | Z7: Decisão; Resposta do escritório (chave da NF-e) | AA7: Decidir a situação (oferta, reembolso, pago de outra forma, NF cancelada ou investigar) e pedir ao escritório a chave de acesso da NF-e.
A8: NF-04 | B8: Estação da Central Comércio de Doces e Bebidas | C8: Não identificado | D8: — | E8: 66 | F8: 45959.625 | G8: 25.98 | H8: Sem lançamento no app | I8: — | J8: NF 66, Estação da Central Comércio de Doces e Bebidas. Nota recebida e lançada pelo escritório na conta 211005 (fornecedores de bens materiais), ainda sem baixa. | K8: Não (a NF não está no app nem na pasta) | L8: Não | M8: Pelo nome: doces e bebidas (lanche ou evento). Fornecedor sem cadastro no app. Datas de 25 a 29/10/2025: quatro NFs pequenas na mesma semana (RFC, Kalunga, Vira Verão, Estação da Central). Aberta há 306 dias em 31/08/2026. | N8: Não identificado só pelo nome. A busca por nome em bases públicas devolveu empresas de nome parecido, nenhuma confirmada. Use a chave de acesso da NF-e (colunas O a Q). | P8: =IF(LEN(SUBSTITUTE($O8," ",""))=44,MID(SUBSTITUTE($O8," ",""),7,2)&"."&MID(SUBSTITUTE($O8," ",""),9,3)&"."&MID(SUBSTITUTE($O8," ",""),12,3)&"/"&MID(SUBSTITUTE($O8," ",""),15,4)&"-"&MID(SUBSTITUTE($O8," ",""),19,2),"") | Q8: =IF(LEN(SUBSTITUTE($O8," ",""))=44,HYPERLINK("https://cnpja.com/office/"&MID(SUBSTITUTE($O8," ",""),7,14),"Consultar emitente"),"") | W8: Aguarda decisão da igreja | X8: Nenhuma evidência na pasta Tesouraria: busquei por nome do arquivo, número da NF, valor (±R$ 0,01, até 90 dias) e pelo TEXTO de 3.601 PDFs. Nada do fornecedor, da NF nem do valor. (889 PDFs são imagens e não puderam ser lidos por texto.) | Y8: — | Z8: Decisão; Resposta do escritório (chave da NF-e) | AA8: Decidir a situação (oferta, reembolso, pago de outra forma, NF cancelada ou investigar) e pedir ao escritório a chave de acesso da NF-e.
A9: NF-05 | B9: Claudinei Pinhal dos Santos Comércio | C9: Não identificado | D9: — | E9: 31606 | F9: 45980.625 | G9: 112.22 | H9: Sem lançamento no app | I9: — | J9: NF 31606, Claudinei Pinhal dos Santos Comércio. Nota recebida e lançada pelo escritório na conta 211005 (fornecedores de bens materiais), ainda sem baixa. | K9: Não (a NF não está no app nem na pasta) | L9: Não | M9: Ramo não identificado pelo nome. Fornecedor sem cadastro no app. Aberta há 285 dias em 31/08/2026. | N9: Não identificado só pelo nome. A busca por nome em bases públicas devolveu empresas de nome parecido, nenhuma confirmada. Use a chave de acesso da NF-e (colunas O a Q). | P9: =IF(LEN(SUBSTITUTE($O9," ",""))=44,MID(SUBSTITUTE($O9," ",""),7,2)&"."&MID(SUBSTITUTE($O9," ",""),9,3)&"."&MID(SUBSTITUTE($O9," ",""),12,3)&"/"&MID(SUBSTITUTE($O9," ",""),15,4)&"-"&MID(SUBSTITUTE($O9," ",""),19,2),"") | Q9: =IF(LEN(SUBSTITUTE($O9," ",""))=44,HYPERLINK("https://cnpja.com/office/"&MID(SUBSTITUTE($O9," ",""),7,14),"Consultar emitente"),"") | W9: Aguarda decisão da igreja | X9: Nenhuma evidência na pasta Tesouraria: busquei por nome do arquivo, número da NF, valor (±R$ 0,01, até 90 dias) e pelo TEXTO de 3.601 PDFs. Nada do fornecedor, da NF nem do valor. (889 PDFs são imagens e não puderam ser lidos por texto.) | Y9: — | Z9: Decisão; Resposta do escritório (chave da NF-e) | AA9: Decidir a situação (oferta, reembolso, pago de outra forma, NF cancelada ou investigar) e pedir ao escritório a chave de acesso da NF-e.
A10: NF-06 | B10: SOS Sobrado Malhas | C10: Não identificado | D10: — | E10: 3763 | F10: 46130.625 | G10: 143 | H10: Sem lançamento no app | I10: — | J10: NF 3763, SOS Sobrado Malhas. Nota recebida e lançada pelo escritório na conta 211005 (fornecedores de bens materiais), ainda sem baixa. | K10: Não (a NF não está no app nem na pasta) | L10: Não | M10: Pelo nome: malhas e confecção. Fornecedor sem cadastro no app. Aberta há 135 dias em 31/08/2026. | N10: Não identificado só pelo nome. A busca por nome em bases públicas devolveu empresas de nome parecido, nenhuma confirmada. Use a chave de acesso da NF-e (colunas O a Q). | P10: =IF(LEN(SUBSTITUTE($O10," ",""))=44,MID(SUBSTITUTE($O10," ",""),7,2)&"."&MID(SUBSTITUTE($O10," ",""),9,3)&"."&MID(SUBSTITUTE($O10," ",""),12,3)&"/"&MID(SUBSTITUTE($O10," ",""),15,4)&"-"&MID(SUBSTITUTE($O10," ",""),19,2),"") | Q10: =IF(LEN(SUBSTITUTE($O10," ",""))=44,HYPERLINK("https://cnpja.com/office/"&MID(SUBSTITUTE($O10," ",""),7,14),"Consultar emitente"),"") | W10: Aguarda decisão da igreja | X10: Nenhuma evidência na pasta Tesouraria: busquei por nome do arquivo, número da NF, valor (±R$ 0,01, até 90 dias) e pelo TEXTO de 3.601 PDFs. Nada do fornecedor, da NF nem do valor. (889 PDFs são imagens e não puderam ser lidos por texto.) | Y10: — | Z10: Decisão; Resposta do escritório (chave da NF-e) | AA10: Decidir a situação (oferta, reembolso, pago de outra forma, NF cancelada ou investigar) e pedir ao escritório a chave de acesso da NF-e.
A11: NF-07 | B11: Tech Brasil Comércio e Serviços | C11: Não identificado | D11: — | E11: 9922 | F11: 46140.625 | G11: 104.4 | H11: Sem lançamento no app | I11: — | J11: NF 9922, Tech Brasil Comércio e Serviços. Nota recebida e lançada pelo escritório na conta 211005 (fornecedores de bens materiais), ainda sem baixa. | K11: Não (a NF não está no app nem na pasta) | L11: Não | M11: Pelo nome: comércio e serviços, provavelmente informática. Fornecedor sem cadastro no app. Aberta há 125 dias em 31/08/2026. | N11: Não identificado só pelo nome. A busca por nome em bases públicas devolveu empresas de nome parecido, nenhuma confirmada. Use a chave de acesso da NF-e (colunas O a Q). | P11: =IF(LEN(SUBSTITUTE($O11," ",""))=44,MID(SUBSTITUTE($O11," ",""),7,2)&"."&MID(SUBSTITUTE($O11," ",""),9,3)&"."&MID(SUBSTITUTE($O11," ",""),12,3)&"/"&MID(SUBSTITUTE($O11," ",""),15,4)&"-"&MID(SUBSTITUTE($O11," ",""),19,2),"") | Q11: =IF(LEN(SUBSTITUTE($O11," ",""))=44,HYPERLINK("https://cnpja.com/office/"&MID(SUBSTITUTE($O11," ",""),7,14),"Consultar emitente"),"") | W11: Aguarda decisão da igreja | X11: Nenhuma evidência na pasta Tesouraria: busquei por nome do arquivo, número da NF, valor (±R$ 0,01, até 90 dias) e pelo TEXTO de 3.601 PDFs. Nada do fornecedor, da NF nem do valor. (889 PDFs são imagens e não puderam ser lidos por texto.) | Y11: — | Z11: Decisão; Resposta do escritório (chave da NF-e) | AA11: Decidir a situação (oferta, reembolso, pago de outra forma, NF cancelada ou investigar) e pedir ao escritório a chave de acesso da NF-e.
A12: NF-08 | B12: Del Castilho Madeiras e Construção | C12: 22.753.989/0001-47 (matriz) | D12: Rua Bispo Lacerda, 28, Del Castilho, Rio de Janeiro/RJ, CEP 21051-120. Tel. (21) 2501-3034. Razão social: DEL CASTILHO MADEIRAS E CONSTRUCAO LTDA; nome fantasia: ATACADAO DEL CASTILHO. | E12: 24553 | F12: 46244.625 | G12: 255.3 | H12: Sem lançamento no app (histórico do fornecedor: Material de Consumo) | I12: (histórico do fornecedor: Administração · Ornamentação) | J12: NF 24553, Del Castilho Madeiras e Construção. Nota recebida e lançada pelo escritório na conta 211005 (fornecedores de bens materiais), ainda sem baixa. | K12: Sim, na pasta Tesouraria (não está anexada no app) | L12: Sim: em dinheiro, 10/08/2026 (Caixa Auxiliar). Não consta como pagamento no app | M12: Pela Receita: comércio de materiais de construção (Atacadão Del Castilho). Fornecedor cadastrado. Tem 2 pagamentos em ago/2025 (R$ 159,00 e R$ 780,03, ambos na Caixinha), de outro período e de outro valor. Aberta há 21 dias em 31/08/2026. | N12: Confirmado pela própria NF-e: emitente Del Castilho Madeiras e Construção LTDA; destinatário Quarta Igreja Batista RJ (CNPJ 27.639.285/0001-61); valor R$ 255,30. Endereço da Receita Federal. | O12: 33260822753989000147550070000245531000754460 | P12: =IF(LEN(SUBSTITUTE($O12," ",""))=44,MID(SUBSTITUTE($O12," ",""),7,2)&"."&MID(SUBSTITUTE($O12," ",""),9,3)&"."&MID(SUBSTITUTE($O12," ",""),12,3)&"/"&MID(SUBSTITUTE($O12," ",""),15,4)&"-"&MID(SUBSTITUTE($O12," ",""),19,2),"") | Q12: =IF(LEN(SUBSTITUTE($O12," ",""))=44,HYPERLINK("https://cnpja.com/office/"&MID(SUBSTITUTE($O12," ",""),7,14),"Consultar emitente"),"") | R12: Pago de Outra Forma | V12: Dinheiro | W12: Automática pela pasta | X12: NF-e 24553 (R$ 255,30, emitida em 10/08/2026 15:35, autorizada, destinatário: a igreja) com o carimbo "PG ESPÉCIE" no Caixa Auxiliar de 10/08/2026. O valor confere no texto do PDF. | Y12: 2026 _ ARQUIVOS DE MOVIMENTO CONTÁBIL/08 - AGO-2026/02. CAIXA AUXILIAR/10.AGO/10.08.2026 - R$255,30 _ NF24553 _ DEL CASTILHO MADEIRAS E CONSTRUCOES _ PG ESPECIE.pdf | Z12: Resposta ao escritório | AA12: Informar ao escritório: pago em dinheiro em 10/08/2026; enviar a NF-e e o comprovante. (O pagamento não está lançado no app: fica para a tesouraria, não foi alterado.)
A13: NF-09 | B13: C Cadamuro Comércio de Utilidades Automotivas | C13: Não identificado | D13: — | E13: 53836 | F13: 46260.625 | G13: 149.38 | H13: Sem lançamento no app | I13: — | J13: NF 53836, C Cadamuro Comércio de Utilidades Automotivas. Nota recebida e lançada pelo escritório na conta 211005 (fornecedores de bens materiais), ainda sem baixa. | K13: Não (a NF não está no app nem na pasta) | L13: Não | M13: Pelo nome: utilidades automotivas. Fornecedor sem cadastro no app. Aberta há 5 dias em 31/08/2026. | N13: Não identificado só pelo nome. A busca por nome em bases públicas devolveu empresas de nome parecido, nenhuma confirmada. Use a chave de acesso da NF-e (colunas O a Q). | P13: =IF(LEN(SUBSTITUTE($O13," ",""))=44,MID(SUBSTITUTE($O13," ",""),7,2)&"."&MID(SUBSTITUTE($O13," ",""),9,3)&"."&MID(SUBSTITUTE($O13," ",""),12,3)&"/"&MID(SUBSTITUTE($O13," ",""),15,4)&"-"&MID(SUBSTITUTE($O13," ",""),19,2),"") | Q13: =IF(LEN(SUBSTITUTE($O13," ",""))=44,HYPERLINK("https://cnpja.com/office/"&MID(SUBSTITUTE($O13," ",""),7,14),"Consultar emitente"),"") | W13: Aguarda decisão da igreja | X13: Nenhuma evidência na pasta Tesouraria: busquei por nome do arquivo, número da NF, valor (±R$ 0,01, até 90 dias) e pelo TEXTO de 3.601 PDFs. Nada do fornecedor, da NF nem do valor. (889 PDFs são imagens e não puderam ser lidos por texto.) | Y13: — | Z13: Decisão; Resposta do escritório (chave da NF-e) | AA13: Decidir a situação (oferta, reembolso, pago de outra forma, NF cancelada ou investigar) e pedir ao escritório a chave de acesso da NF-e.
A14: NF-10 | B14: Goldensky Comércio Digital | C14: 36.470.020/0002-54 (filial) | D14: Rua Amazonas da Silva, 271, Vila Guilherme, São Paulo/SP, CEP 02051-000. Tel. (11) 5061-0215. Razão social: GOLDENSKY COMERCIO DIGITAL LTDA. | E14: 1621752 | F14: 46265.625 | G14: 443.95 | H14: Sem lançamento no app | I14: — | J14: NF 1621752, Goldensky Comércio Digital. Nota recebida e lançada pelo escritório na conta 211005 (fornecedores de bens materiais), ainda sem baixa. | K14: Não (a NF não está no app nem na pasta) | L14: Não | M14: Pela Receita: comércio varejista de equipamentos e suprimentos de informática. Fornecedor cadastrado, sem nenhum lançamento. NF de 31/08: se foi paga em setembro, o app mostraria; não mostra. Aberta há 0 dias em 31/08/2026. | N14: CNPJ do cadastro do app; razão social e endereço da Receita Federal (consulta de 13/10/2026). Atenção: é uma FILIAL. Confirmar pela chave se a NF 1621752 saiu dela. | P14: =IF(LEN(SUBSTITUTE($O14," ",""))=44,MID(SUBSTITUTE($O14," ",""),7,2)&"."&MID(SUBSTITUTE($O14," ",""),9,3)&"."&MID(SUBSTITUTE($O14," ",""),12,3)&"/"&MID(SUBSTITUTE($O14," ",""),15,4)&"-"&MID(SUBSTITUTE($O14," ",""),19,2),"") | Q14: =IF(LEN(SUBSTITUTE($O14," ",""))=44,HYPERLINK("https://cnpja.com/office/"&MID(SUBSTITUTE($O14," ",""),7,14),"Consultar emitente"),"") | W14: Aguarda decisão da igreja | X14: Nenhuma evidência na pasta Tesouraria: busquei por nome do arquivo, número da NF, valor (±R$ 0,01, até 90 dias) e pelo TEXTO de 3.601 PDFs. Nada do fornecedor, da NF nem do valor. (889 PDFs são imagens e não puderam ser lidos por texto.) | Y14: — | Z14: Decisão; Resposta do escritório (chave da NF-e) | AA14: Decidir a situação (oferta, reembolso, pago de outra forma, NF cancelada ou investigar) e pedir ao escritório a chave de acesso da NF-e.
A15: NF-11 | B15: D Flesh Serviços e Conveniências | C15: 02.052.410/0001-01 (matriz) | D15: Largo Aluno Horácio Lucas, 17, loja 17-A, Engenho Velho, Rio de Janeiro/RJ, CEP 20271-180. Razão social: D FLESH SERVICOS E CONVENIENCIAS LTDA; nomes fantasia: KIMANIA, KIFOTOS, KIKASKINHA, KICOPIAS. | E15: 25597 | F15: 45575.625 | G15: 137.28 | H15: Sem lançamento no app (histórico do fornecedor: Publicidade e Propaganda) | I15: (histórico do fornecedor: Administração · Institucional) | J15: NF 25597, D Flesh Serviços e Conveniências. Nota recebida e lançada pelo escritório na conta 211006 (fornecedores de bens e serviços), ainda sem baixa. | K15: Não (a NF 25597 não está na pasta; só existe a resposta da igreja) | L15: Sim: em espécie, pelo Pr. Patrick (resposta de jan/2026); não passou pelo caixa da igreja | M15: Pela Receita: fotocópias (Kimania, Kifotos, Kicopias). Fornecedor cadastrado. Tem 6 pagamentos (R$ 1.270,00 no total); os mais próximos: R$ 250,00 em 07/11/2024 e R$ 100,00 em 26/03/2025. Nenhum de R$ 137,28. Aberta há 690 dias em 31/08/2026. | N15: CNPJ do cadastro do app; razão social e endereço da Receita Federal (consulta de 13/10/2026). Atividade: fotocópias. | P15: =IF(LEN(SUBSTITUTE($O15," ",""))=44,MID(SUBSTITUTE($O15," ",""),7,2)&"."&MID(SUBSTITUTE($O15," ",""),9,3)&"."&MID(SUBSTITUTE($O15," ",""),12,3)&"/"&MID(SUBSTITUTE($O15," ",""),15,4)&"-"&MID(SUBSTITUTE($O15," ",""),19,2),"") | Q15: =IF(LEN(SUBSTITUTE($O15," ",""))=44,HYPERLINK("https://cnpja.com/office/"&MID(SUBSTITUTE($O15," ",""),7,14),"Consultar emitente"),"") | R15: Oferta para a Igreja | S15: Pr. Patrick (nome completo a confirmar) | W15: Automática pela pasta | X15: Resposta da igreja ao escritório (jan/2026): "Foi pago em espécie pelo Pr. Patrick, e ofertado." A NF 25597 não está na pasta; só há a resposta. | Y15: Pendências AL/01_2026_ALPL_CONT_111_SOLICITAÇÃO_DOCUMENTOS_CONTABILIDADE_QIBRJ.xlsx, aba SERVIÇOS_TOMADOS, coluna "Resposta do cliente" | Z15: Documento; Resposta ao escritório | AA15: Obter o termo de doação assinado pelo Pr. Patrick (R$ 137,28, NF 25597) e informar ao escritório que é doação não monetária.
A16: NF-12 | B16: Paulo Cid Lopes Pinto | C16: Não identificado | D16: — | E16: 184 | F16: 45603.625 | G16: 150 | H16: Sem lançamento no app | I16: — | J16: NF 184, Paulo Cid Lopes Pinto. Nota recebida e lançada pelo escritório na conta 211006 (fornecedores de bens e serviços), ainda sem baixa. | K16: Não (falta a nota de cancelamento; só há a resposta e o extrato) | L16: Sim: R$ 160,00 em 26/06/2024 (valor diferente da NF de R$ 150,00) | M16: Pessoa física ou MEI. Fornecedor sem cadastro. O app tem pagamentos que citam Paulo Cid nas observações, lançados como SOLTECX Construções e Soluções: R$ 160,00 (26/06/2024 e 18/07/2025), R$ 726,70 (06/02/2025), R$ 558,00 (24/03/2025) e R$ 210,00 (27/02/2026). Nenhum de R$ 150,00. Aberta há 662 dias em 31/08/2026. | N16: Não identificado só pelo nome. A busca por nome em bases públicas devolveu empresas de nome parecido, nenhuma confirmada. Use a chave de acesso da NF-e (colunas O a Q). Pessoa física ou MEI; o app registra pagamentos que citam Paulo Cid como SOLTECX Construções e Soluções (outro nome da mesma pessoa ou empresa?), sem CNPJ. | P16: =IF(LEN(SUBSTITUTE($O16," ",""))=44,MID(SUBSTITUTE($O16," ",""),7,2)&"."&MID(SUBSTITUTE($O16," ",""),9,3)&"."&MID(SUBSTITUTE($O16," ",""),12,3)&"/"&MID(SUBSTITUTE($O16," ",""),15,4)&"-"&MID(SUBSTITUTE($O16," ",""),19,2),"") | Q16: =IF(LEN(SUBSTITUTE($O16," ",""))=44,HYPERLINK("https://cnpja.com/office/"&MID(SUBSTITUTE($O16," ",""),7,14),"Consultar emitente"),"") | R16: NF Cancelada | W16: Automática pela pasta | X16: Resposta da igreja ao escritório (jan/2026): "Foi solicitado o cancelamento desta NF pois o valor pago foi de R$ 160,00." O extrato do Bradesco de 26/06/2024 mostra o PIX para Paulo Cid, e o app registra R$ 160,00 nessa data (lançado como SOLTECX). | Y16: Pendências AL/01_2026_ALPL_CONT_111_SOLICITAÇÃO_DOCUMENTOS_CONTABILIDADE_QIBRJ.xlsx, aba SERVIÇOS_TOMADOS, coluna "Resposta do cliente"; extrato do Bradesco em 2024 _ ARQUIVOS DE MOVIMENTO CONTÁBIL/06 - JUN-2024 _ MALOTES/25.JUN/25.06.2024 - R$280,00 _ ANTUB ANDAIMES _ PG BANKLINE.pdf | Z16: Documento; Resposta ao escritório | AA16: Obter a prova do cancelamento da NF 184 (nota de cancelamento ou e-mail do emitente) e a NF do pagamento de R$ 160,00. O escritório ainda mostra a NF 184 em aberto.
A17: NF-13 | B17: R E M Áudio e Tecnologia | C17: Não identificado | D17: — | E17: 1047 | F17: 45898.625 | G17: 161.3 | H17: Sem lançamento no app | I17: — | J17: NF 1047, R E M Áudio e Tecnologia. Nota recebida e lançada pelo escritório na conta 211006 (fornecedores de bens e serviços), ainda sem baixa. | K17: Não (a NF não está no app nem na pasta) | L17: Não | M17: Pelo nome: áudio e tecnologia (equipamento ou serviço de som). Fornecedor sem cadastro no app. Aberta há 367 dias em 31/08/2026. | N17: Não identificado só pelo nome. A busca por nome em bases públicas devolveu empresas de nome parecido, nenhuma confirmada. Use a chave de acesso da NF-e (colunas O a Q). | P17: =IF(LEN(SUBSTITUTE($O17," ",""))=44,MID(SUBSTITUTE($O17," ",""),7,2)&"."&MID(SUBSTITUTE($O17," ",""),9,3)&"."&MID(SUBSTITUTE($O17," ",""),12,3)&"/"&MID(SUBSTITUTE($O17," ",""),15,4)&"-"&MID(SUBSTITUTE($O17," ",""),19,2),"") | Q17: =IF(LEN(SUBSTITUTE($O17," ",""))=44,HYPERLINK("https://cnpja.com/office/"&MID(SUBSTITUTE($O17," ",""),7,14),"Consultar emitente"),"") | W17: Aguarda decisão da igreja | X17: Nenhuma evidência na pasta Tesouraria: busquei por nome do arquivo, número da NF, valor (±R$ 0,01, até 90 dias) e pelo TEXTO de 3.601 PDFs. Nada do fornecedor, da NF nem do valor. (889 PDFs são imagens e não puderam ser lidos por texto.) | Y17: — | Z17: Decisão; Resposta do escritório (chave da NF-e) | AA17: Decidir a situação (oferta, reembolso, pago de outra forma, NF cancelada ou investigar) e pedir ao escritório a chave de acesso da NF-e.
A18: NF-14 | B18: Hotelaria Accor Brasil | C18: 09.967.852/0001-27 (matriz) | D18: Avenida Doutora Ruth Cardoso, 7815, andares 9 e 10, Pinheiros, São Paulo/SP, CEP 05425-905. Tel. (11) 2089-6100. Razão social: HOTELARIA ACCOR BRASIL S/A. | E18: 166376 | F18: 45908.625 | G18: 445.1 | H18: Sem lançamento no app | I18: — | J18: NF 166376, Hotelaria Accor Brasil. Nota recebida e lançada pelo escritório na conta 211006 (fornecedores de bens e serviços), ainda sem baixa. | K18: Sim, na pasta Tesouraria (imagem; não está anexada no app) | L18: Sim: em dinheiro, 08/09/2025 (Caixa Auxiliar) | M18: Pela Receita: hotéis. Provável viagem ou evento. Fornecedor sem cadastro no app. Aberta há 357 dias em 31/08/2026. | N18: Matriz confirmada na Receita (a razão social confere). Cada hotel tem CNPJ de filial (mesma raiz 09.967.852): a chave diz em qual hotel foi a hospedagem. | P18: =IF(LEN(SUBSTITUTE($O18," ",""))=44,MID(SUBSTITUTE($O18," ",""),7,2)&"."&MID(SUBSTITUTE($O18," ",""),9,3)&"."&MID(SUBSTITUTE($O18," ",""),12,3)&"/"&MID(SUBSTITUTE($O18," ",""),15,4)&"-"&MID(SUBSTITUTE($O18," ",""),19,2),"") | Q18: =IF(LEN(SUBSTITUTE($O18," ",""))=44,HYPERLINK("https://cnpja.com/office/"&MID(SUBSTITUTE($O18," ",""),7,14),"Consultar emitente"),"") | R18: Pago de Outra Forma | V18: Dinheiro | W18: Automática pela pasta | X18: NF 166376 (Hotelaria Accor, R$ 445,10) com o carimbo "PG ESPÉCIE", datada de 08/09/2025, no Caixa Auxiliar do malote de ago/2025. O PDF é uma imagem: nome, data e valor conferem; o conteúdo não pôde ser lido. | Y18: 2025 _ ARQUIVOS DE MOVIMENTO CONTÁBIL/2025 _ 3º TRIMESTRE E OUTUBRO/08 - AGO-2025 _ MALOTE/02. CAIXA AUXILIAR/08.09.2025 - R$445,10 _ NF166376 _ HOTELARIA ACCOR BRASIL SA _ PG ESPÉCIE.pdf | Z18: Resposta ao escritório | AA18: Informar pagamento em dinheiro em 08/09/2025 e enviar o arquivo. Conferir visualmente o PDF antes de enviar.
A19: NF-15 | B19: Hidro Sistemas Contra Incêndio | C19: Não identificado | D19: — | E19: 7392 | F19: 45996.625 | G19: 50 | H19: Sem lançamento no app | I19: — | J19: NF 7392, Hidro Sistemas Contra Incêndio. Nota recebida e lançada pelo escritório na conta 211006 (fornecedores de bens e serviços), ainda sem baixa. | K19: Não (a NF não está no app nem na pasta) | L19: Não | M19: Pelo nome: serviço de combate a incêndio (extintores ou mangueiras). Fornecedor sem cadastro no app. Aberta há 269 dias em 31/08/2026. | N19: Não identificado só pelo nome. A busca por nome em bases públicas devolveu empresas de nome parecido, nenhuma confirmada. Use a chave de acesso da NF-e (colunas O a Q). | P19: =IF(LEN(SUBSTITUTE($O19," ",""))=44,MID(SUBSTITUTE($O19," ",""),7,2)&"."&MID(SUBSTITUTE($O19," ",""),9,3)&"."&MID(SUBSTITUTE($O19," ",""),12,3)&"/"&MID(SUBSTITUTE($O19," ",""),15,4)&"-"&MID(SUBSTITUTE($O19," ",""),19,2),"") | Q19: =IF(LEN(SUBSTITUTE($O19," ",""))=44,HYPERLINK("https://cnpja.com/office/"&MID(SUBSTITUTE($O19," ",""),7,14),"Consultar emitente"),"") | W19: Aguarda decisão da igreja | X19: Nenhuma evidência na pasta Tesouraria: busquei por nome do arquivo, número da NF, valor (±R$ 0,01, até 90 dias) e pelo TEXTO de 3.601 PDFs. Nada do fornecedor, da NF nem do valor. (889 PDFs são imagens e não puderam ser lidos por texto.) | Y19: — | Z19: Decisão; Resposta do escritório (chave da NF-e) | AA19: Decidir a situação (oferta, reembolso, pago de outra forma, NF cancelada ou investigar) e pedir ao escritório a chave de acesso da NF-e.
A20: NF-16 | B20: Castor Administração de Hotelaria | C20: Não identificado | D20: — | E20: 230048 | F20: 46147.625 | G20: 258.63 | H20: Sem lançamento no app | I20: — | J20: NF 230048, Castor Administração de Hotelaria. Nota recebida e lançada pelo escritório na conta 211006 (fornecedores de bens e serviços), ainda sem baixa. | K20: Não (a NF não está no app nem na pasta) | L20: Não | M20: Pelo nome: hospedagem (hotel). Provável viagem ou evento. Fornecedor sem cadastro no app. Duas NFs do mesmo hotel com 6 dias de diferença (esta e a 230334). Aberta há 118 dias em 31/08/2026. | N20: Não identificado só pelo nome. A busca por nome em bases públicas devolveu empresas de nome parecido, nenhuma confirmada. Use a chave de acesso da NF-e (colunas O a Q). | P20: =IF(LEN(SUBSTITUTE($O20," ",""))=44,MID(SUBSTITUTE($O20," ",""),7,2)&"."&MID(SUBSTITUTE($O20," ",""),9,3)&"."&MID(SUBSTITUTE($O20," ",""),12,3)&"/"&MID(SUBSTITUTE($O20," ",""),15,4)&"-"&MID(SUBSTITUTE($O20," ",""),19,2),"") | Q20: =IF(LEN(SUBSTITUTE($O20," ",""))=44,HYPERLINK("https://cnpja.com/office/"&MID(SUBSTITUTE($O20," ",""),7,14),"Consultar emitente"),"") | W20: Aguarda decisão da igreja | X20: Nenhuma evidência na pasta Tesouraria: busquei por nome do arquivo, número da NF, valor (±R$ 0,01, até 90 dias) e pelo TEXTO de 3.601 PDFs. Nada do fornecedor, da NF nem do valor. (889 PDFs são imagens e não puderam ser lidos por texto.) | Y20: — | Z20: Decisão; Resposta do escritório (chave da NF-e) | AA20: Decidir a situação (oferta, reembolso, pago de outra forma, NF cancelada ou investigar) e pedir ao escritório a chave de acesso da NF-e.
A21: NF-17 | B21: Castor Administração de Hotelaria | C21: Não identificado | D21: — | E21: 230334 | F21: 46153.625 | G21: 278.56 | H21: Sem lançamento no app | I21: — | J21: NF 230334, Castor Administração de Hotelaria. Nota recebida e lançada pelo escritório na conta 211006 (fornecedores de bens e serviços), ainda sem baixa. | K21: Não (a NF não está no app nem na pasta) | L21: Não | M21: Pelo nome: hospedagem (hotel). Provável viagem ou evento. Fornecedor sem cadastro no app. Duas NFs do mesmo hotel com 6 dias de diferença (esta e a 230048). Aberta há 112 dias em 31/08/2026. | N21: Não identificado só pelo nome. A busca por nome em bases públicas devolveu empresas de nome parecido, nenhuma confirmada. Use a chave de acesso da NF-e (colunas O a Q). | P21: =IF(LEN(SUBSTITUTE($O21," ",""))=44,MID(SUBSTITUTE($O21," ",""),7,2)&"."&MID(SUBSTITUTE($O21," ",""),9,3)&"."&MID(SUBSTITUTE($O21," ",""),12,3)&"/"&MID(SUBSTITUTE($O21," ",""),15,4)&"-"&MID(SUBSTITUTE($O21," ",""),19,2),"") | Q21: =IF(LEN(SUBSTITUTE($O21," ",""))=44,HYPERLINK("https://cnpja.com/office/"&MID(SUBSTITUTE($O21," ",""),7,14),"Consultar emitente"),"") | W21: Aguarda decisão da igreja | X21: Nenhuma evidência na pasta Tesouraria: busquei por nome do arquivo, número da NF, valor (±R$ 0,01, até 90 dias) e pelo TEXTO de 3.601 PDFs. Nada do fornecedor, da NF nem do valor. (889 PDFs são imagens e não puderam ser lidos por texto.) | Y21: — | Z21: Decisão; Resposta do escritório (chave da NF-e) | AA21: Decidir a situação (oferta, reembolso, pago de outra forma, NF cancelada ou investigar) e pedir ao escritório a chave de acesso da NF-e.
B23: Total das 17 NFs | G23: =SUM(G5:G21)

Sheet Resumo
A1: Quanto da decisão a pasta já resolveu
A3: Situação das 17 NFs | B3: NFs | C3: Valor (R$) | D3: Quais
A4: 1. Classificadas automaticamente pela pasta | B4: =COUNTIF(Decisão!$W$5:$W$21,"Automática pela pasta") | C4: =SUMIF(Decisão!$W$5:$W$21,"Automática pela pasta",Decisão!$G$5:$G$21) | D4: Del Castilho NF 24553; D Flesh NF 25597; Paulo Cid NF 184; Hotelaria Accor NF 166376
A5: 2. Ainda exigem decisão da igreja | B5: =COUNTIF(Decisão!$W$5:$W$21,"Aguarda decisão da igreja") | C5: =SUMIF(Decisão!$W$5:$W$21,"Aguarda decisão da igreja",Decisão!$G$5:$G$21) | D5: As outras 13 NFs (sem nenhum rastro na pasta)
A6: Total | B6: =B4+B5 | C6: =C4+C5
A8: O que cada situação já tem
A9: Oferta para a Igreja | B9: =COUNTIF(Decisão!$R$5:$R$21,A9) | C9: =SUMIF(Decisão!$R$5:$R$21,A9,Decisão!$G$5:$G$21)
A10: Reembolso | B10: =COUNTIF(Decisão!$R$5:$R$21,A10) | C10: =SUMIF(Decisão!$R$5:$R$21,A10,Decisão!$G$5:$G$21)
A11: Pago de Outra Forma | B11: =COUNTIF(Decisão!$R$5:$R$21,A11) | C11: =SUMIF(Decisão!$R$5:$R$21,A11,Decisão!$G$5:$G$21)
A12: NF Cancelada | B12: =COUNTIF(Decisão!$R$5:$R$21,A12) | C12: =SUMIF(Decisão!$R$5:$R$21,A12,Decisão!$G$5:$G$21)
A13: Precisa Investigar | B13: =COUNTIF(Decisão!$R$5:$R$21,A13) | C13: =SUMIF(Decisão!$R$5:$R$21,A13,Decisão!$G$5:$G$21)
A14: Sem situação (aguardam você) | B14: =COUNTBLANK(Decisão!$R$5:$R$21) | C14: =SUMIF(Decisão!$R$5:$R$21,"",Decisão!$G$5:$G$21)
A16: O que ainda falta
A17: Decisão da igreja | B17: =COUNTIF(Decisão!$Z$5:$Z$21,"*Decisão*")
A18: Documentação | B18: =COUNTIF(Decisão!$Z$5:$Z$21,"*Documento*")
A19: Resposta da igreja ao escritório | B19: =COUNTIF(Decisão!$Z$5:$Z$21,"*Resposta ao escritório*")
A20: Resposta do escritório (chave da NF-e) | B20: =COUNTIF(Decisão!$Z$5:$Z$21,"*Resposta do escritório*")
A22: Uma NF pode estar em mais de uma lista de pendência restante.

Sheet 1 Classificadas pela pasta
A1: NFs classificadas automaticamente com evidência da pasta
A3: ID | B3: Fornecedor | C3: NF | D3: Valor (R$) | E3: Situação | F3: Forma / doador | G3: Justificativa | H3: Documento utilizado | I3: Próximo passo
A4: NF-08 | B4: Del Castilho Madeiras e Construção | C4: 24553 | D4: 255.3 | E4: Pago de Outra Forma | F4: Dinheiro | G4: NF-e 24553 (R$ 255,30, emitida em 10/08/2026 15:35, autorizada, destinatário: a igreja) com o carimbo "PG ESPÉCIE" no Caixa Auxiliar de 10/08/2026. O valor confere no texto do PDF. | H4: 2026 _ ARQUIVOS DE MOVIMENTO CONTÁBIL/08 - AGO-2026/02. CAIXA AUXILIAR/10.AGO/10.08.2026 - R$255,30 _ NF24553 _ DEL CASTILHO MADEIRAS E CONSTRUCOES _ PG ESPECIE.pdf | I4: Informar ao escritório: pago em dinheiro em 10/08/2026; enviar a NF-e e o comprovante. (O pagamento não está lançado no app: fica para a tesouraria, não foi alterado.)
A5: NF-11 | B5: D Flesh Serviços e Conveniências | C5: 25597 | D5: 137.28 | E5: Oferta para a Igreja | F5: Pr. Patrick (nome completo a confirmar) | G5: Resposta da igreja ao escritório (jan/2026): "Foi pago em espécie pelo Pr. Patrick, e ofertado." A NF 25597 não está na pasta; só há a resposta. | H5: Pendências AL/01_2026_ALPL_CONT_111_SOLICITAÇÃO_DOCUMENTOS_CONTABILIDADE_QIBRJ.xlsx, aba SERVIÇOS_TOMADOS, coluna "Resposta do cliente" | I5: Obter o termo de doação assinado pelo Pr. Patrick (R$ 137,28, NF 25597) e informar ao escritório que é doação não monetária.
A6: NF-12 | B6: Paulo Cid Lopes Pinto | C6: 184 | D6: 150 | E6: NF Cancelada | F6: — | G6: Resposta da igreja ao escritório (jan/2026): "Foi solicitado o cancelamento desta NF pois o valor pago foi de R$ 160,00." O extrato do Bradesco de 26/06/2024 mostra o PIX para Paulo Cid, e o app registra R$ 160,00 nessa data (lançado como SOLTECX). | H6: Pendências AL/01_2026_ALPL_CONT_111_SOLICITAÇÃO_DOCUMENTOS_CONTABILIDADE_QIBRJ.xlsx, aba SERVIÇOS_TOMADOS, coluna "Resposta do cliente"; extrato do Bradesco em 2024 _ ARQUIVOS DE MOVIMENTO CONTÁBIL/06 - JUN-2024 _ MALOTES/25.JUN/25.06.2024 - R$280,00 _ ANTUB ANDAIMES _ PG BANKLINE.pdf | I6: Obter a prova do cancelamento da NF 184 (nota de cancelamento ou e-mail do emitente) e a NF do pagamento de R$ 160,00. O escritório ainda mostra a NF 184 em aberto.
A7: NF-14 | B7: Hotelaria Accor Brasil | C7: 166376 | D7: 445.1 | E7: Pago de Outra Forma | F7: Dinheiro | G7: NF 166376 (Hotelaria Accor, R$ 445,10) com o carimbo "PG ESPÉCIE", datada de 08/09/2025, no Caixa Auxiliar do malote de ago/2025. O PDF é uma imagem: nome, data e valor conferem; o conteúdo não pôde ser lido. | H7: 2025 _ ARQUIVOS DE MOVIMENTO CONTÁBIL/2025 _ 3º TRIMESTRE E OUTUBRO/08 - AGO-2025 _ MALOTE/02. CAIXA AUXILIAR/08.09.2025 - R$445,10 _ NF166376 _ HOTELARIA ACCOR BRASIL SA _ PG ESPÉCIE.pdf | I7: Informar pagamento em dinheiro em 08/09/2025 e enviar o arquivo. Conferir visualmente o PDF antes de enviar.

Sheet 2 Exigem decisão da igreja
A1: NFs sem nenhum rastro na pasta: só a igreja decide
A3: ID | B3: Fornecedor | C3: NF | D3: Data | E3: Valor (R$) | F3: O que a pasta mostra | G3: Pista pelo nome ou Receita
A4: NF-01 | B4: RFC Comércio de Miudezas | C4: 6942 | D4: 45955.625 | E4: 125.88 | F4: Nenhuma evidência na pasta Tesouraria: busquei por nome do arquivo, número da NF, valor (±R$ 0,01, até 90 dias) e pelo TEXTO de 3.601 PDFs. Nada do fornecedor, da NF nem do valor. (889 PDFs são imagens e não puderam ser lidos por texto.) | G4: Pelo nome: material diverso (miudezas).
A5: NF-02 | B5: Kalunga | C5: 344169 | D5: 45957.625 | E5: 84.2 | F5: Nenhuma evidência na pasta Tesouraria: busquei por nome do arquivo, número da NF, valor (±R$ 0,01, até 90 dias) e pelo TEXTO de 3.601 PDFs. Nada do fornecedor, da NF nem do valor. (889 PDFs são imagens e não puderam ser lidos por texto.) | G5: Pela Receita: papelaria.
A6: NF-03 | B6: Vira Verão Bazar | C6: 64 | D6: 45958.625 | E6: 25 | F6: Nenhuma evidência na pasta Tesouraria: busquei por nome do arquivo, número da NF, valor (±R$ 0,01, até 90 dias) e pelo TEXTO de 3.601 PDFs. Nada do fornecedor, da NF nem do valor. (889 PDFs são imagens e não puderam ser lidos por texto.) | G6: Pelo nome: bazar, artigos diversos.
A7: NF-04 | B7: Estação da Central Comércio de Doces e Bebidas | C7: 66 | D7: 45959.625 | E7: 25.98 | F7: Nenhuma evidência na pasta Tesouraria: busquei por nome do arquivo, número da NF, valor (±R$ 0,01, até 90 dias) e pelo TEXTO de 3.601 PDFs. Nada do fornecedor, da NF nem do valor. (889 PDFs são imagens e não puderam ser lidos por texto.) | G7: Pelo nome: doces e bebidas (lanche ou evento).
A8: NF-05 | B8: Claudinei Pinhal dos Santos Comércio | C8: 31606 | D8: 45980.625 | E8: 112.22 | F8: Nenhuma evidência na pasta Tesouraria: busquei por nome do arquivo, número da NF, valor (±R$ 0,01, até 90 dias) e pelo TEXTO de 3.601 PDFs. Nada do fornecedor, da NF nem do valor. (889 PDFs são imagens e não puderam ser lidos por texto.) | G8: Ramo não identificado pelo nome.
A9: NF-06 | B9: SOS Sobrado Malhas | C9: 3763 | D9: 46130.625 | E9: 143 | F9: Nenhuma evidência na pasta Tesouraria: busquei por nome do arquivo, número da NF, valor (±R$ 0,01, até 90 dias) e pelo TEXTO de 3.601 PDFs. Nada do fornecedor, da NF nem do valor. (889 PDFs são imagens e não puderam ser lidos por texto.) | G9: Pelo nome: malhas e confecção.
A10: NF-07 | B10: Tech Brasil Comércio e Serviços | C10: 9922 | D10: 46140.625 | E10: 104.4 | F10: Nenhuma evidência na pasta Tesouraria: busquei por nome do arquivo, número da NF, valor (±R$ 0,01, até 90 dias) e pelo TEXTO de 3.601 PDFs. Nada do fornecedor, da NF nem do valor. (889 PDFs são imagens e não puderam ser lidos por texto.) | G10: Pelo nome: comércio e serviços, provavelmente informática.
A11: NF-09 | B11: C Cadamuro Comércio de Utilidades Automotivas | C11: 53836 | D11: 46260.625 | E11: 149.38 | F11: Nenhuma evidência na pasta Tesouraria: busquei por nome do arquivo, número da NF, valor (±R$ 0,01, até 90 dias) e pelo TEXTO de 3.601 PDFs. Nada do fornecedor, da NF nem do valor. (889 PDFs são imagens e não puderam ser lidos por texto.) | G11: Pelo nome: utilidades automotivas.
A12: NF-10 | B12: Goldensky Comércio Digital | C12: 1621752 | D12: 46265.625 | E12: 443.95 | F12: Nenhuma evidência na pasta Tesouraria: busquei por nome do arquivo, número da NF, valor (±R$ 0,01, até 90 dias) e pelo TEXTO de 3.601 PDFs. Nada do fornecedor, da NF nem do valor. (889 PDFs são imagens e não puderam ser lidos por texto.) | G12: Pela Receita: comércio varejista de equipamentos e suprimentos de informática.
A13: NF-13 | B13: R E M Áudio e Tecnologia | C13: 1047 | D13: 45898.625 | E13: 161.3 | F13: Nenhuma evidência na pasta Tesouraria: busquei por nome do arquivo, número da NF, valor (±R$ 0,01, até 90 dias) e pelo TEXTO de 3.601 PDFs. Nada do fornecedor, da NF nem do valor. (889 PDFs são imagens e não puderam ser lidos por texto.) | G13: Pelo nome: áudio e tecnologia (equipamento ou serviço de som).
A14: NF-15 | B14: Hidro Sistemas Contra Incêndio | C14: 7392 | D14: 45996.625 | E14: 50 | F14: Nenhuma evidência na pasta Tesouraria: busquei por nome do arquivo, número da NF, valor (±R$ 0,01, até 90 dias) e pelo TEXTO de 3.601 PDFs. Nada do fornecedor, da NF nem do valor. (889 PDFs são imagens e não puderam ser lidos por texto.) | G14: Pelo nome: serviço de combate a incêndio (extintores ou mangueiras).
A15: NF-16 | B15: Castor Administração de Hotelaria | C15: 230048 | D15: 46147.625 | E15: 258.63 | F15: Nenhuma evidência na pasta Tesouraria: busquei por nome do arquivo, número da NF, valor (±R$ 0,01, até 90 dias) e pelo TEXTO de 3.601 PDFs. Nada do fornecedor, da NF nem do valor. (889 PDFs são imagens e não puderam ser lidos por texto.) | G15: Pelo nome: hospedagem (hotel). Provável viagem ou evento.
A16: NF-17 | B16: Castor Administração de Hotelaria | C16: 230334 | D16: 46153.625 | E16: 278.56 | F16: Nenhuma evidência na pasta Tesouraria: busquei por nome do arquivo, número da NF, valor (±R$ 0,01, até 90 dias) e pelo TEXTO de 3.601 PDFs. Nada do fornecedor, da NF nem do valor. (889 PDFs são imagens e não puderam ser lidos por texto.) | G16: Pelo nome: hospedagem (hotel). Provável viagem ou evento.

Sheet 3 Exigem documentação
A1: Documentos que ainda faltam, mesmo nas NFs já classificadas
A3: ID | B3: Fornecedor | C3: NF | D3: Valor (R$) | E3: Situação | F3: O que falta
A4: NF-11 | B4: D Flesh Serviços e Conveniências | C4: 25597 | D4: 137.28 | E4: Oferta para a Igreja | F4: Obter o termo de doação assinado pelo Pr. Patrick (R$ 137,28, NF 25597) e informar ao escritório que é doação não monetária.
A5: NF-12 | B5: Paulo Cid Lopes Pinto | C5: 184 | D5: 150 | E5: NF Cancelada | F5: Obter a prova do cancelamento da NF 184 (nota de cancelamento ou e-mail do emitente) e a NF do pagamento de R$ 160,00. O escritório ainda mostra a NF 184 em aberto.

Sheet 4 Exigem resposta ao escritório
A1: Respostas que a igreja deve enviar ao escritório (e a chave da NF-e que o escritório deve enviar)
A3: ID | B3: Fornecedor | C3: NF | D3: Valor (R$) | E3: Quem responde a quem | F3: O que responder ou pedir
A4: NF-01 | B4: RFC Comércio de Miudezas | C4: 6942 | D4: 125.88 | E4: Escritório responde à igreja (chave da NF-e) | F4: Pedir a chave de acesso (44 dígitos) ou o XML da NF-e. Depois da decisão da igreja, anexar o documento conforme a situação.
A5: NF-02 | B5: Kalunga | C5: 344169 | D5: 84.2 | E5: Escritório responde à igreja (chave da NF-e) | F5: Pedir a chave de acesso (44 dígitos) ou o XML da NF-e. Depois da decisão da igreja, anexar o documento conforme a situação.
A6: NF-03 | B6: Vira Verão Bazar | C6: 64 | D6: 25 | E6: Escritório responde à igreja (chave da NF-e) | F6: Pedir a chave de acesso (44 dígitos) ou o XML da NF-e. Depois da decisão da igreja, anexar o documento conforme a situação.
A7: NF-04 | B7: Estação da Central Comércio de Doces e Bebidas | C7: 66 | D7: 25.98 | E7: Escritório responde à igreja (chave da NF-e) | F7: Pedir a chave de acesso (44 dígitos) ou o XML da NF-e. Depois da decisão da igreja, anexar o documento conforme a situação.
A8: NF-05 | B8: Claudinei Pinhal dos Santos Comércio | C8: 31606 | D8: 112.22 | E8: Escritório responde à igreja (chave da NF-e) | F8: Pedir a chave de acesso (44 dígitos) ou o XML da NF-e. Depois da decisão da igreja, anexar o documento conforme a situação.
A9: NF-06 | B9: SOS Sobrado Malhas | C9: 3763 | D9: 143 | E9: Escritório responde à igreja (chave da NF-e) | F9: Pedir a chave de acesso (44 dígitos) ou o XML da NF-e. Depois da decisão da igreja, anexar o documento conforme a situação.
A10: NF-07 | B10: Tech Brasil Comércio e Serviços | C10: 9922 | D10: 104.4 | E10: Escritório responde à igreja (chave da NF-e) | F10: Pedir a chave de acesso (44 dígitos) ou o XML da NF-e. Depois da decisão da igreja, anexar o documento conforme a situação.
A11: NF-08 | B11: Del Castilho Madeiras e Construção | C11: 24553 | D11: 255.3 | E11: Igreja responde ao escritório | F11: Informar ao escritório: pago em dinheiro em 10/08/2026; enviar a NF-e e o comprovante. (O pagamento não está lançado no app: fica para a tesouraria, não foi alterado.)
A12: NF-09 | B12: C Cadamuro Comércio de Utilidades Automotivas | C12: 53836 | D12: 149.38 | E12: Escritório responde à igreja (chave da NF-e) | F12: Pedir a chave de acesso (44 dígitos) ou o XML da NF-e. Depois da decisão da igreja, anexar o documento conforme a situação.
A13: NF-10 | B13: Goldensky Comércio Digital | C13: 1621752 | D13: 443.95 | E13: Escritório responde à igreja (chave da NF-e) | F13: Pedir a chave de acesso (44 dígitos) ou o XML da NF-e. Depois da decisão da igreja, anexar o documento conforme a situação.
A14: NF-11 | B14: D Flesh Serviços e Conveniências | C14: 25597 | D14: 137.28 | E14: Igreja responde ao escritório | F14: Obter o termo de doação assinado pelo Pr. Patrick (R$ 137,28, NF 25597) e informar ao escritório que é doação não monetária.
A15: NF-12 | B15: Paulo Cid Lopes Pinto | C15: 184 | D15: 150 | E15: Igreja responde ao escritório | F15: Obter a prova do cancelamento da NF 184 (nota de cancelamento ou e-mail do emitente) e a NF do pagamento de R$ 160,00. O escritório ainda mostra a NF 184 em aberto.
... A20: NF-17 | B20: Castor Administração de Hotelaria | C20: 230334 | D20: 278.56 | E20: Escritório responde à igreja (chave da NF-e) | F20: Pedir a chave de acesso (44 dígitos) ou o XML da NF-e. Depois da decisão da igreja, anexar o documento conforme a situação.

Sheet Pedido ao escritório
A1: Texto para o escritório e as NFs que ainda dependem da chave (13 de 17)
A2: Olá. Para rastrearmos as pendências das contas 211005 e 211006 (saldo de 31/08/2026), peço a chave de acesso (44 dígitos) ou o XML das NF-e recebidas listadas abaixo, e, quando houver, o CNPJ e o endereço do emitente. Para a Kalunga, que tem várias lojas, precisamos saber qual unidade emitiu a nota. As demais 4 NFs da lista original (Del Castilho, Hotelaria Accor, D Flesh e Paulo Cid) já têm resposta e enviaremos à parte. Obrigada.
A8: ID | B8: Fornecedor | C8: Nº da NF | D8: Data | E8: Valor (R$) | F8: Chave de acesso (o escritório preenche)
A9: NF-01 | B9: RFC Comércio de Miudezas | C9: 6942 | D9: 45955.625 | E9: 125.88
A10: NF-02 | B10: Kalunga | C10: 344169 | D10: 45957.625 | E10: 84.2
A11: NF-03 | B11: Vira Verão Bazar | C11: 64 | D11: 45958.625 | E11: 25
A12: NF-04 | B12: Estação da Central Comércio de Doces e Bebidas | C12: 66 | D12: 45959.625 | E12: 25.98
A13: NF-05 | B13: Claudinei Pinhal dos Santos Comércio | C13: 31606 | D13: 45980.625 | E13: 112.22
A14: NF-06 | B14: SOS Sobrado Malhas | C14: 3763 | D14: 46130.625 | E14: 143
A15: NF-07 | B15: Tech Brasil Comércio e Serviços | C15: 9922 | D15: 46140.625 | E15: 104.4
A16: NF-09 | B16: C Cadamuro Comércio de Utilidades Automotivas | C16: 53836 | D16: 46260.625 | E16: 149.38
A17: NF-10 | B17: Goldensky Comércio Digital | C17: 1621752 | D17: 46265.625 | E17: 443.95
A18: NF-13 | B18: R E M Áudio e Tecnologia | C18: 1047 | D18: 45898.625 | E18: 161.3
A19: NF-15 | B19: Hidro Sistemas Contra Incêndio | C19: 7392 | D19: 45996.625 | E19: 50
A20: NF-16 | B20: Castor Administração de Hotelaria | C20: 230048 | D20: 46147.625 | E20: 258.63
A21: NF-17 | B21: Castor Administração de Hotelaria | C21: 230334 | D21: 46153.625 | E21: 278.56

Sheet Como preencher
A1: Como escolher a Situação
A3: Situação | B3: Quando escolher | C3: O que isso significa para a contabilidade
A4: Oferta para a Igreja | B4: Alguém comprou com dinheiro próprio, a NF saiu no CNPJ da igreja e a pessoa disse que estava ofertando. Informe o doador. | C4: Doação não monetária: o escritório lança despesa (ou estoque, ou imobilizado) e a receita de doação. Não passa por caixa nem banco. Pede termo de doação assinado pelo doador.
A5: Reembolso | B5: Alguém pagou do próprio bolso e a igreja deve devolver (ou já devolveu). Informe a pessoa e se já foi pago. | C5: A despesa vale na data da NF e a igreja deve à pessoa. Se já foi pago, o app precisa do comprovante do reembolso.
A6: Pago de Outra Forma | B6: A igreja pagou, mas o app não mostra: PIX, TED, dinheiro, cartão ou outro. Informe a forma. | C6: O pagamento existe; falta ligá-lo à NF e (se for dinheiro) lançá-lo no app.
A7: NF Cancelada | B7: A NF foi cancelada ou substituída pelo emitente. | C7: O escritório baixa a NF contra o cancelamento. Pede a prova do cancelamento e a NF do valor que foi de fato pago.
A8: Precisa Investigar | B8: Você não sabe. O escritório volta a perguntar. | C8: Continua aberta na contabilidade até haver uma resposta.
A10: Cores
A11: Verde | B11: Preenchido automaticamente com evidência da pasta. Você pode corrigir.
A12: Amarelo | B12: Espera a sua decisão.
A13: Laranja | B13: Falta preencher um campo que a Situação escolhida exige.
A14: Cinza | B14: Campo que não vale para a Situação escolhida.
A16: Como achar o CNPJ e o local da compra
A17: A chave de acesso da NF-e tem 44 dígitos; os dígitos 7 a 20 são o CNPJ do emitente. Cole a chave na coluna O: o CNPJ aparece na P e o link da Q abre a consulta da empresa.
A18: CNPJ com final diferente de /0001 é filial: indica a loja ou o hotel. Vale para Kalunga e Goldensky.
A19: A busca de fornecedores por nome em bases públicas devolveu empresas homônimas, por isso 11 fornecedores seguem sem CNPJ.
A21: Esta planilha só registra decisões e evidências. Nenhum dado do app foi alterado, nenhum lançamento criado e nada reclassificado.
