Workbook

Sheet Decisão
A1: 17 NFs sem pagamento identificado: planilha de decisão
A2: Levantamento de 13/10/2026 (saldo do escritório em 31/08/2026). Colunas A a N: o que o app, o escritório e a Receita Federal mostram. Colunas O a Q: rastreio pela chave da NF-e (a chave de 44 dígitos traz o CNPJ de quem emitiu). Colunas R a W (amarelas): a sua decisão; as que não se aplicam à Situação ficam cinza e as que faltam ficam laranja.
A3: O QUE SABEMOS | O3: RASTREAR PELA NF-e | R3: SUA DECISÃO
A4: ID | B4: Fornecedor | C4: CNPJ do emitente | D4: Endereço do emitente | E4: Nº da NF | F4: Data | G4: Valor (R$) | H4: Categoria atual | I4: Centro atual | J4: Descrição | K4: Existe documento anexado? | L4: Existe pagamento localizado? | M4: Observações | N4: Confiança e fonte do CNPJ e endereço | O4: Chave de acesso da NF-e (44 dígitos; preencha) | P4: CNPJ pela chave (automático) | Q4: Consultar emitente (automático) | R4: Situação | S4: Nome do doador (se Oferta) | T4: Pessoa a reembolsar (se Reembolso) | U4: Pagamento já realizado? (se Reembolso) | V4: Forma de pagamento (se Pago de Outra Forma) | W4: Sua observação
A5: NF-01 | B5: RFC Comércio de Miudezas | C5: Não identificado | D5: — | E5: 6942 | F5: 45955.625 | G5: 125.88 | H5: Sem lançamento no app | I5: — | J5: NF 6942, RFC Comércio de Miudezas. Nota recebida e lançada pelo escritório na conta 211005 (fornecedores de bens materiais), ainda sem baixa. | K5: Não (a NF não está no app) | L5: Não | M5: Pelo nome: material diverso (miudezas). Fornecedor sem cadastro no app. Aberta há 310 dias em 31/08/2026. | N5: Não identificado só pelo nome. A busca por nome em bases públicas devolveu empresas de nome parecido, nenhuma confirmada. Use a chave de acesso da NF-e (colunas O a Q). | P5: =IF(LEN(SUBSTITUTE($O5," ",""))=44,MID(SUBSTITUTE($O5," ",""),7,2)&"."&MID(SUBSTITUTE($O5," ",""),9,3)&"."&MID(SUBSTITUTE($O5," ",""),12,3)&"/"&MID(SUBSTITUTE($O5," ",""),15,4)&"-"&MID(SUBSTITUTE($O5," ",""),19,2),"") | Q5: =IF(LEN(SUBSTITUTE($O5," ",""))=44,HYPERLINK("https://cnpja.com/office/"&MID(SUBSTITUTE($O5," ",""),7,14),"Consultar emitente"),"")
A6: NF-02 | B6: Kalunga | C6: 43.283.811/0001-50 (matriz) | D6: Rua da Mooca, 766, andares 4 e 5, Mooca, São Paulo/SP, CEP 03104-010. Tel. (11) 3346-9600. Razão social: KALUNGA SA. | E6: 344169 | F6: 45957.625 | G6: 84.2 | H6: Sem lançamento no app | I6: — | J6: NF 344169, Kalunga. Nota recebida e lançada pelo escritório na conta 211005 (fornecedores de bens materiais), ainda sem baixa. | K6: Não (a NF não está no app) | L6: Não | M6: Pela Receita: papelaria. Fornecedor sem cadastro no app. Aberta há 308 dias em 31/08/2026. | N6: Matriz confirmada na Receita (a razão social confere). A NF pode ter saído de uma filial (a Kalunga tem lojas no Rio, como Norte Shopping/Cachambi): a chave diz qual. | P6: =IF(LEN(SUBSTITUTE($O6," ",""))=44,MID(SUBSTITUTE($O6," ",""),7,2)&"."&MID(SUBSTITUTE($O6," ",""),9,3)&"."&MID(SUBSTITUTE($O6," ",""),12,3)&"/"&MID(SUBSTITUTE($O6," ",""),15,4)&"-"&MID(SUBSTITUTE($O6," ",""),19,2),"") | Q6: =IF(LEN(SUBSTITUTE($O6," ",""))=44,HYPERLINK("https://cnpja.com/office/"&MID(SUBSTITUTE($O6," ",""),7,14),"Consultar emitente"),"")
A7: NF-03 | B7: Vira Verão Bazar | C7: Não identificado | D7: — | E7: 64 | F7: 45958.625 | G7: 25 | H7: Sem lançamento no app | I7: — | J7: NF 64, Vira Verão Bazar. Nota recebida e lançada pelo escritório na conta 211005 (fornecedores de bens materiais), ainda sem baixa. | K7: Não (a NF não está no app) | L7: Não | M7: Pelo nome: bazar, artigos diversos. Fornecedor sem cadastro no app. Aberta há 307 dias em 31/08/2026. | N7: Não identificado só pelo nome. A busca por nome em bases públicas devolveu empresas de nome parecido, nenhuma confirmada. Use a chave de acesso da NF-e (colunas O a Q). | P7: =IF(LEN(SUBSTITUTE($O7," ",""))=44,MID(SUBSTITUTE($O7," ",""),7,2)&"."&MID(SUBSTITUTE($O7," ",""),9,3)&"."&MID(SUBSTITUTE($O7," ",""),12,3)&"/"&MID(SUBSTITUTE($O7," ",""),15,4)&"-"&MID(SUBSTITUTE($O7," ",""),19,2),"") | Q7: =IF(LEN(SUBSTITUTE($O7," ",""))=44,HYPERLINK("https://cnpja.com/office/"&MID(SUBSTITUTE($O7," ",""),7,14),"Consultar emitente"),"")
A8: NF-04 | B8: Estação da Central Comércio de Doces e Bebidas | C8: Não identificado | D8: — | E8: 66 | F8: 45959.625 | G8: 25.98 | H8: Sem lançamento no app | I8: — | J8: NF 66, Estação da Central Comércio de Doces e Bebidas. Nota recebida e lançada pelo escritório na conta 211005 (fornecedores de bens materiais), ainda sem baixa. | K8: Não (a NF não está no app) | L8: Não | M8: Pelo nome: doces e bebidas (lanche ou evento). Fornecedor sem cadastro no app. Datas de 25 a 29/10/2025: quatro NFs pequenas na mesma semana (RFC, Kalunga, Vira Verão, Estação da Central). Aberta há 306 dias em 31/08/2026. | N8: Não identificado só pelo nome. A busca por nome em bases públicas devolveu empresas de nome parecido, nenhuma confirmada. Use a chave de acesso da NF-e (colunas O a Q). | P8: =IF(LEN(SUBSTITUTE($O8," ",""))=44,MID(SUBSTITUTE($O8," ",""),7,2)&"."&MID(SUBSTITUTE($O8," ",""),9,3)&"."&MID(SUBSTITUTE($O8," ",""),12,3)&"/"&MID(SUBSTITUTE($O8," ",""),15,4)&"-"&MID(SUBSTITUTE($O8," ",""),19,2),"") | Q8: =IF(LEN(SUBSTITUTE($O8," ",""))=44,HYPERLINK("https://cnpja.com/office/"&MID(SUBSTITUTE($O8," ",""),7,14),"Consultar emitente"),"")
A9: NF-05 | B9: Claudinei Pinhal dos Santos Comércio | C9: Não identificado | D9: — | E9: 31606 | F9: 45980.625 | G9: 112.22 | H9: Sem lançamento no app | I9: — | J9: NF 31606, Claudinei Pinhal dos Santos Comércio. Nota recebida e lançada pelo escritório na conta 211005 (fornecedores de bens materiais), ainda sem baixa. | K9: Não (a NF não está no app) | L9: Não | M9: Ramo não identificado pelo nome. Fornecedor sem cadastro no app. Aberta há 285 dias em 31/08/2026. | N9: Não identificado só pelo nome. A busca por nome em bases públicas devolveu empresas de nome parecido, nenhuma confirmada. Use a chave de acesso da NF-e (colunas O a Q). | P9: =IF(LEN(SUBSTITUTE($O9," ",""))=44,MID(SUBSTITUTE($O9," ",""),7,2)&"."&MID(SUBSTITUTE($O9," ",""),9,3)&"."&MID(SUBSTITUTE($O9," ",""),12,3)&"/"&MID(SUBSTITUTE($O9," ",""),15,4)&"-"&MID(SUBSTITUTE($O9," ",""),19,2),"") | Q9: =IF(LEN(SUBSTITUTE($O9," ",""))=44,HYPERLINK("https://cnpja.com/office/"&MID(SUBSTITUTE($O9," ",""),7,14),"Consultar emitente"),"")
A10: NF-06 | B10: SOS Sobrado Malhas | C10: Não identificado | D10: — | E10: 3763 | F10: 46130.625 | G10: 143 | H10: Sem lançamento no app | I10: — | J10: NF 3763, SOS Sobrado Malhas. Nota recebida e lançada pelo escritório na conta 211005 (fornecedores de bens materiais), ainda sem baixa. | K10: Não (a NF não está no app) | L10: Não | M10: Pelo nome: malhas e confecção. Fornecedor sem cadastro no app. Aberta há 135 dias em 31/08/2026. | N10: Não identificado só pelo nome. A busca por nome em bases públicas devolveu empresas de nome parecido, nenhuma confirmada. Use a chave de acesso da NF-e (colunas O a Q). | P10: =IF(LEN(SUBSTITUTE($O10," ",""))=44,MID(SUBSTITUTE($O10," ",""),7,2)&"."&MID(SUBSTITUTE($O10," ",""),9,3)&"."&MID(SUBSTITUTE($O10," ",""),12,3)&"/"&MID(SUBSTITUTE($O10," ",""),15,4)&"-"&MID(SUBSTITUTE($O10," ",""),19,2),"") | Q10: =IF(LEN(SUBSTITUTE($O10," ",""))=44,HYPERLINK("https://cnpja.com/office/"&MID(SUBSTITUTE($O10," ",""),7,14),"Consultar emitente"),"")
A11: NF-07 | B11: Tech Brasil Comércio e Serviços | C11: Não identificado | D11: — | E11: 9922 | F11: 46140.625 | G11: 104.4 | H11: Sem lançamento no app | I11: — | J11: NF 9922, Tech Brasil Comércio e Serviços. Nota recebida e lançada pelo escritório na conta 211005 (fornecedores de bens materiais), ainda sem baixa. | K11: Não (a NF não está no app) | L11: Não | M11: Pelo nome: comércio e serviços, provavelmente informática. Fornecedor sem cadastro no app. Aberta há 125 dias em 31/08/2026. | N11: Não identificado só pelo nome. A busca por nome em bases públicas devolveu empresas de nome parecido, nenhuma confirmada. Use a chave de acesso da NF-e (colunas O a Q). | P11: =IF(LEN(SUBSTITUTE($O11," ",""))=44,MID(SUBSTITUTE($O11," ",""),7,2)&"."&MID(SUBSTITUTE($O11," ",""),9,3)&"."&MID(SUBSTITUTE($O11," ",""),12,3)&"/"&MID(SUBSTITUTE($O11," ",""),15,4)&"-"&MID(SUBSTITUTE($O11," ",""),19,2),"") | Q11: =IF(LEN(SUBSTITUTE($O11," ",""))=44,HYPERLINK("https://cnpja.com/office/"&MID(SUBSTITUTE($O11," ",""),7,14),"Consultar emitente"),"")
A12: NF-08 | B12: Del Castilho Madeiras e Construção | C12: 22.753.989/0001-47 (matriz) | D12: Rua Bispo Lacerda, 28, Del Castilho, Rio de Janeiro/RJ, CEP 21051-120. Tel. (21) 2501-3034. Razão social: DEL CASTILHO MADEIRAS E CONSTRUCAO LTDA; nome fantasia: ATACADAO DEL CASTILHO. | E12: 24553 | F12: 46244.625 | G12: 255.3 | H12: Sem lançamento no app (histórico do fornecedor: Material de Consumo) | I12: (histórico do fornecedor: Administração · Ornamentação) | J12: NF 24553, Del Castilho Madeiras e Construção. Nota recebida e lançada pelo escritório na conta 211005 (fornecedores de bens materiais), ainda sem baixa. | K12: Não (a NF não está no app) | L12: Não | M12: Pela Receita: comércio de materiais de construção (Atacadão Del Castilho). Fornecedor cadastrado. Tem 2 pagamentos em ago/2025 (R$ 159,00 e R$ 780,03, ambos na Caixinha), de outro período e de outro valor. Aberta há 21 dias em 31/08/2026. | N12: CNPJ do cadastro do app; razão social e endereço da Receita Federal (consulta de 13/10/2026). Situação: ativa. | P12: =IF(LEN(SUBSTITUTE($O12," ",""))=44,MID(SUBSTITUTE($O12," ",""),7,2)&"."&MID(SUBSTITUTE($O12," ",""),9,3)&"."&MID(SUBSTITUTE($O12," ",""),12,3)&"/"&MID(SUBSTITUTE($O12," ",""),15,4)&"-"&MID(SUBSTITUTE($O12," ",""),19,2),"") | Q12: =IF(LEN(SUBSTITUTE($O12," ",""))=44,HYPERLINK("https://cnpja.com/office/"&MID(SUBSTITUTE($O12," ",""),7,14),"Consultar emitente"),"")
A13: NF-09 | B13: C Cadamuro Comércio de Utilidades Automotivas | C13: Não identificado | D13: — | E13: 53836 | F13: 46260.625 | G13: 149.38 | H13: Sem lançamento no app | I13: — | J13: NF 53836, C Cadamuro Comércio de Utilidades Automotivas. Nota recebida e lançada pelo escritório na conta 211005 (fornecedores de bens materiais), ainda sem baixa. | K13: Não (a NF não está no app) | L13: Não | M13: Pelo nome: utilidades automotivas. Fornecedor sem cadastro no app. Aberta há 5 dias em 31/08/2026. | N13: Não identificado só pelo nome. A busca por nome em bases públicas devolveu empresas de nome parecido, nenhuma confirmada. Use a chave de acesso da NF-e (colunas O a Q). | P13: =IF(LEN(SUBSTITUTE($O13," ",""))=44,MID(SUBSTITUTE($O13," ",""),7,2)&"."&MID(SUBSTITUTE($O13," ",""),9,3)&"."&MID(SUBSTITUTE($O13," ",""),12,3)&"/"&MID(SUBSTITUTE($O13," ",""),15,4)&"-"&MID(SUBSTITUTE($O13," ",""),19,2),"") | Q13: =IF(LEN(SUBSTITUTE($O13," ",""))=44,HYPERLINK("https://cnpja.com/office/"&MID(SUBSTITUTE($O13," ",""),7,14),"Consultar emitente"),"")
A14: NF-10 | B14: Goldensky Comércio Digital | C14: 36.470.020/0002-54 (filial) | D14: Rua Amazonas da Silva, 271, Vila Guilherme, São Paulo/SP, CEP 02051-000. Tel. (11) 5061-0215. Razão social: GOLDENSKY COMERCIO DIGITAL LTDA. | E14: 1621752 | F14: 46265.625 | G14: 443.95 | H14: Sem lançamento no app | I14: — | J14: NF 1621752, Goldensky Comércio Digital. Nota recebida e lançada pelo escritório na conta 211005 (fornecedores de bens materiais), ainda sem baixa. | K14: Não (a NF não está no app) | L14: Não | M14: Pela Receita: comércio varejista de equipamentos e suprimentos de informática. Fornecedor cadastrado, sem nenhum lançamento. NF de 31/08: se foi paga em setembro, o app mostraria; não mostra. Aberta há 0 dias em 31/08/2026. | N14: CNPJ do cadastro do app; razão social e endereço da Receita Federal (consulta de 13/10/2026). Atenção: é uma FILIAL. Confirmar pela chave se a NF 1621752 saiu dela. | P14: =IF(LEN(SUBSTITUTE($O14," ",""))=44,MID(SUBSTITUTE($O14," ",""),7,2)&"."&MID(SUBSTITUTE($O14," ",""),9,3)&"."&MID(SUBSTITUTE($O14," ",""),12,3)&"/"&MID(SUBSTITUTE($O14," ",""),15,4)&"-"&MID(SUBSTITUTE($O14," ",""),19,2),"") | Q14: =IF(LEN(SUBSTITUTE($O14," ",""))=44,HYPERLINK("https://cnpja.com/office/"&MID(SUBSTITUTE($O14," ",""),7,14),"Consultar emitente"),"")
A15: NF-11 | B15: D Flesh Serviços e Conveniências | C15: 02.052.410/0001-01 (matriz) | D15: Largo Aluno Horácio Lucas, 17, loja 17-A, Engenho Velho, Rio de Janeiro/RJ, CEP 20271-180. Razão social: D FLESH SERVICOS E CONVENIENCIAS LTDA; nomes fantasia: KIMANIA, KIFOTOS, KIKASKINHA, KICOPIAS. | E15: 25597 | F15: 45575.625 | G15: 137.28 | H15: Sem lançamento no app (histórico do fornecedor: Publicidade e Propaganda) | I15: (histórico do fornecedor: Administração · Institucional) | J15: NF 25597, D Flesh Serviços e Conveniências. Nota recebida e lançada pelo escritório na conta 211006 (fornecedores de bens e serviços), ainda sem baixa. | K15: Não (a NF não está no app) | L15: Não | M15: Pela Receita: fotocópias (Kimania, Kifotos, Kicopias). Fornecedor cadastrado. Tem 6 pagamentos (R$ 1.270,00 no total); os mais próximos: R$ 250,00 em 07/11/2024 e R$ 100,00 em 26/03/2025. Nenhum de R$ 137,28. Aberta há 690 dias em 31/08/2026. | N15: CNPJ do cadastro do app; razão social e endereço da Receita Federal (consulta de 13/10/2026). Atividade: fotocópias. | P15: =IF(LEN(SUBSTITUTE($O15," ",""))=44,MID(SUBSTITUTE($O15," ",""),7,2)&"."&MID(SUBSTITUTE($O15," ",""),9,3)&"."&MID(SUBSTITUTE($O15," ",""),12,3)&"/"&MID(SUBSTITUTE($O15," ",""),15,4)&"-"&MID(SUBSTITUTE($O15," ",""),19,2),"") | Q15: =IF(LEN(SUBSTITUTE($O15," ",""))=44,HYPERLINK("https://cnpja.com/office/"&MID(SUBSTITUTE($O15," ",""),7,14),"Consultar emitente"),"")
A16: NF-12 | B16: Paulo Cid Lopes Pinto | C16: Não identificado | D16: — | E16: 184 | F16: 45603.625 | G16: 150 | H16: Sem lançamento no app | I16: — | J16: NF 184, Paulo Cid Lopes Pinto. Nota recebida e lançada pelo escritório na conta 211006 (fornecedores de bens e serviços), ainda sem baixa. | K16: Não (a NF não está no app) | L16: Não | M16: Pessoa física ou MEI. Fornecedor sem cadastro. O app tem pagamentos que citam Paulo Cid nas observações, lançados como SOLTECX Construções e Soluções: R$ 160,00 (26/06/2024 e 18/07/2025), R$ 726,70 (06/02/2025), R$ 558,00 (24/03/2025) e R$ 210,00 (27/02/2026). Nenhum de R$ 150,00. Aberta há 662 dias em 31/08/2026. | N16: Não identificado só pelo nome. A busca por nome em bases públicas devolveu empresas de nome parecido, nenhuma confirmada. Use a chave de acesso da NF-e (colunas O a Q). Pessoa física ou MEI; o app registra pagamentos que citam Paulo Cid como SOLTECX Construções e Soluções (outro nome da mesma pessoa ou empresa?), sem CNPJ. | P16: =IF(LEN(SUBSTITUTE($O16," ",""))=44,MID(SUBSTITUTE($O16," ",""),7,2)&"."&MID(SUBSTITUTE($O16," ",""),9,3)&"."&MID(SUBSTITUTE($O16," ",""),12,3)&"/"&MID(SUBSTITUTE($O16," ",""),15,4)&"-"&MID(SUBSTITUTE($O16," ",""),19,2),"") | Q16: =IF(LEN(SUBSTITUTE($O16," ",""))=44,HYPERLINK("https://cnpja.com/office/"&MID(SUBSTITUTE($O16," ",""),7,14),"Consultar emitente"),"")
... A21: NF-17 | B21: Castor Administração de Hotelaria | C21: Não identificado | D21: — | E21: 230334 | F21: 46153.625 | G21: 278.56 | H21: Sem lançamento no app | I21: — | J21: NF 230334, Castor Administração de Hotelaria. Nota recebida e lançada pelo escritório na conta 211006 (fornecedores de bens e serviços), ainda sem baixa. | K21: Não (a NF não está no app) | L21: Não | M21: Pelo nome: hospedagem (hotel). Provável viagem ou evento. Fornecedor sem cadastro no app. Duas NFs do mesmo hotel com 6 dias de diferença (esta e a 230048). Aberta há 112 dias em 31/08/2026. | N21: Não identificado só pelo nome. A busca por nome em bases públicas devolveu empresas de nome parecido, nenhuma confirmada. Use a chave de acesso da NF-e (colunas O a Q). | P21: =IF(LEN(SUBSTITUTE($O21," ",""))=44,MID(SUBSTITUTE($O21," ",""),7,2)&"."&MID(SUBSTITUTE($O21," ",""),9,3)&"."&MID(SUBSTITUTE($O21," ",""),12,3)&"/"&MID(SUBSTITUTE($O21," ",""),15,4)&"-"&MID(SUBSTITUTE($O21," ",""),19,2),"") | Q21: =IF(LEN(SUBSTITUTE($O21," ",""))=44,HYPERLINK("https://cnpja.com/office/"&MID(SUBSTITUTE($O21," ",""),7,14),"Consultar emitente"),"")
B23: Total das 17 NFs | G23: =SUM(G5:G21)

Sheet Resumo
A1: Andamento da decisão
A3: Situação | B3: NFs | C3: Valor (R$)
A4: Oferta para a Igreja | B4: =COUNTIF(Decisão!$R$5:$R$21,A4) | C4: =SUMIF(Decisão!$R$5:$R$21,A4,Decisão!$G$5:$G$21)
A5: Reembolso | B5: =COUNTIF(Decisão!$R$5:$R$21,A5) | C5: =SUMIF(Decisão!$R$5:$R$21,A5,Decisão!$G$5:$G$21)
A6: Pago de Outra Forma | B6: =COUNTIF(Decisão!$R$5:$R$21,A6) | C6: =SUMIF(Decisão!$R$5:$R$21,A6,Decisão!$G$5:$G$21)
A7: Precisa Investigar | B7: =COUNTIF(Decisão!$R$5:$R$21,A7) | C7: =SUMIF(Decisão!$R$5:$R$21,A7,Decisão!$G$5:$G$21)
A8: Ainda sem decisão | B8: =COUNTBLANK(Decisão!$R$5:$R$21) | C8: =SUMIF(Decisão!$R$5:$R$21,"",Decisão!$G$5:$G$21)
A9: Total | B9: =SUM(B4:B8) | C9: =SUM(C4:C8)
A11: Linhas com dados faltando
A12: Oferta sem nome do doador | B12: =COUNTIFS(Decisão!$R$5:$R$21,"Oferta para a Igreja",Decisão!$S$5:$S$21,"")
A13: Reembolso sem pessoa a reembolsar | B13: =COUNTIFS(Decisão!$R$5:$R$21,"Reembolso",Decisão!$T$5:$T$21,"")
A14: Reembolso sem 'pagamento já realizado?' | B14: =COUNTIFS(Decisão!$R$5:$R$21,"Reembolso",Decisão!$U$5:$U$21,"")
A15: Pago de outra forma sem a forma | B15: =COUNTIFS(Decisão!$R$5:$R$21,"Pago de Outra Forma",Decisão!$V$5:$V$21,"")
A17: Rastreio do emitente
A18: NFs com CNPJ identificado | B18: =COUNTIF(Decisão!$C$5:$C$21,"*/0*")
A19: NFs ainda sem CNPJ | B19: =COUNTIF(Decisão!$C$5:$C$21,"Não identificado")
A20: NFs com chave preenchida | B20: =COUNTA(Decisão!$O$5:$O$21)
A22: Pronto para o 2º relatório quando 'Ainda sem decisão' e todas as linhas faltando forem zero.

Sheet Pedido ao escritório
A1: Texto para enviar ao escritório e lista das NFs
A2: Olá. Para rastrearmos e baixarmos as pendências das contas 211005 e 211006 (saldo de 31/08/2026), peço o relatório das NF-e recebidas listadas abaixo, com a CHAVE DE ACESSO (44 dígitos) ou o XML de cada uma, e, quando houver, o CNPJ e o endereço do emitente. Em especial para Kalunga e Hotelaria Accor, que têm várias filiais: precisamos saber a unidade (loja ou hotel) que emitiu a nota. Obrigada.
A8: ID | B8: Fornecedor | C8: Nº da NF | D8: Data | E8: Valor (R$) | F8: Chave de acesso (o escritório preenche)
A9: NF-01 | B9: RFC Comércio de Miudezas | C9: 6942 | D9: 45955.625 | E9: 125.88
A10: NF-02 | B10: Kalunga | C10: 344169 | D10: 45957.625 | E10: 84.2
A11: NF-03 | B11: Vira Verão Bazar | C11: 64 | D11: 45958.625 | E11: 25
A12: NF-04 | B12: Estação da Central Comércio de Doces e Bebidas | C12: 66 | D12: 45959.625 | E12: 25.98
A13: NF-05 | B13: Claudinei Pinhal dos Santos Comércio | C13: 31606 | D13: 45980.625 | E13: 112.22
A14: NF-06 | B14: SOS Sobrado Malhas | C14: 3763 | D14: 46130.625 | E14: 143
A15: NF-07 | B15: Tech Brasil Comércio e Serviços | C15: 9922 | D15: 46140.625 | E15: 104.4
A16: NF-08 | B16: Del Castilho Madeiras e Construção | C16: 24553 | D16: 46244.625 | E16: 255.3
A17: NF-09 | B17: C Cadamuro Comércio de Utilidades Automotivas | C17: 53836 | D17: 46260.625 | E17: 149.38
A18: NF-10 | B18: Goldensky Comércio Digital | C18: 1621752 | D18: 46265.625 | E18: 443.95
A19: NF-11 | B19: D Flesh Serviços e Conveniências | C19: 25597 | D19: 45575.625 | E19: 137.28
A20: NF-12 | B20: Paulo Cid Lopes Pinto | C20: 184 | D20: 45603.625 | E20: 150
... A25: NF-17 | B25: Castor Administração de Hotelaria | C25: 230334 | D25: 46153.625 | E25: 278.56

Sheet Como preencher
A1: Como escolher a Situação
A3: Situação | B3: Quando escolher | C3: O que isso significa para a contabilidade
A4: Oferta para a Igreja | B4: Alguém comprou com dinheiro próprio, a NF saiu no CNPJ da igreja e a pessoa disse que estava ofertando. Não houve nem haverá reembolso. Informe o doador. | C4: Doação não monetária: o escritório lança despesa (ou estoque, ou imobilizado) e a receita de doação. Não passa por caixa nem por banco. Pede termo de doação assinado pelo doador.
A5: Reembolso | B5: Alguém pagou do próprio bolso e a igreja deve devolver (ou já devolveu). Informe a pessoa e se o reembolso já foi pago. | C5: A despesa vale na data da NF, e a igreja deve à pessoa. Se já foi pago, o app precisa do comprovante do reembolso; se não, vira conta a pagar para a pessoa.
A6: Pago de Outra Forma | B6: A igreja pagou, mas o app não mostra: foi PIX, TED, dinheiro, cartão ou outro. Informe a forma. | C6: O pagamento existe; falta localizá-lo e ligá-lo à NF. Pode ser um pagamento já lançado com outro nome ou valor, ou algo que ficou fora do app.
A7: Precisa Investigar | B7: Você não sabe. O escritório volta a perguntar. | C7: Continua aberta na contabilidade até haver uma resposta.
A9: Como achar o CNPJ e o local da compra
A10: 1. A chave de acesso da NF-e tem 44 dígitos e aparece no DANFE (o PDF da nota), no código de barras e no nome do XML.
A11: 2. Os dígitos 7 a 20 da chave são o CNPJ de quem emitiu. Cole a chave na coluna O da aba Decisão: o CNPJ aparece sozinho na coluna P e o link da coluna Q abre a consulta da empresa (razão social e endereço).
A12: 3. O escritório recebe essas NFs, então tem a chave de todas. A aba 'Pedido ao escritório' traz o texto e a lista prontos.
A13: 4. CNPJ com final diferente de /0001 é filial: indica a loja ou o hotel exato. Vale para Kalunga, Accor e Goldensky.
A14: 5. Para 12 das 17 NFs (11 fornecedores) não foi possível achar o CNPJ só pelo nome: bases públicas devolveram empresas homônimas, e preferi deixar em branco a chutar.
A16: Esta planilha só registra a sua decisão. Nenhum dado do app é alterado, nenhum lançamento é criado e nada é reclassificado.
